spydb/__init__.py
s_pydb-3.0.1.dist-info/LICENSE
s_pydb-3.0.1.dist-info/METADATA
s_pydb-3.0.1.dist-info/WHEEL
s_pydb-3.0.1.dist-info/top_level.txt
s_pydb-3.0.1.dist-info/RECORD
