Metadata-Version: 2.1
Name: s-pydb
Version: 3.0.1
Summary: A simple local file-based database module.
Author: Sanalzio
Author-email: salazio@duck.com
Keywords: python,database
Classifier: Development Status :: 5 - Production/Stable
Classifier: License :: OSI Approved :: GNU General Public License v3 or later (GPLv3+)
Classifier: Intended Audience :: Developers
Classifier: Programming Language :: Python :: 3
Classifier: Operating System :: Unix
Classifier: Operating System :: MacOS :: MacOS X
Classifier: Operating System :: Microsoft :: Windows
License-File: LICENSE
